{
"ID":"21",
"Name":"",
"Exec":"",
"DataList":
[
    {
        "CTID": "21",
        "CTNM": "Taiwan",
        "MaxTemp": "20.9",
        "MeanTemp": "16.7",
        "MinTemp": "13.5",
        "Month": 1
    },
    {
        "CTID": "21",
        "CTNM": "Taiwan",
        "MaxTemp": "21.7",
        "MeanTemp": "17.4",
        "MinTemp": "14.1",
        "Month": 2
    },
    {
        "CTID": "21",
        "CTNM": "Taiwan",
        "MaxTemp": "23.9",
        "MeanTemp": "19.6",
        "MinTemp": "16.1",
        "Month": 3
    },
    {
        "CTID": "21",
        "CTNM": "Taiwan",
        "MaxTemp": "26.8",
        "MeanTemp": "22.7",
        "MinTemp": "19.3",
        "Month": 4
    },
    {
        "CTID": "21",
        "CTNM": "Taiwan",
        "MaxTemp": "29.3",
        "MeanTemp": "25.4",
        "MinTemp": "22.1",
        "Month": 5
    },
    {
        "CTID": "21",
        "CTNM": "Taiwan",
        "MaxTemp": "31.2",
        "MeanTemp": "27.3",
        "MinTemp": "24.1",
        "Month": 6
    },
    {
        "CTID": "21",
        "CTNM": "Taiwan",
        "MaxTemp": "32.3",
        "MeanTemp": "28.1",
        "MinTemp": "24.8",
        "Month": 7
    },
    {
        "CTID": "21",
        "CTNM": "Taiwan",
        "MaxTemp": "31.8",
        "MeanTemp": "27.7",
        "MinTemp": "24.6",
        "Month": 8
    },
    {
        "CTID": "21",
        "CTNM": "Taiwan",
        "MaxTemp": "30.7",
        "MeanTemp": "26.7",
        "MinTemp": "23.6",
        "Month": 9
    },
    {
        "CTID": "21",
        "CTNM": "Taiwan",
        "MaxTemp": "28.4",
        "MeanTemp": "24.3",
        "MinTemp": "21.2",
        "Month": 10
    },
    {
        "CTID": "21",
        "CTNM": "Taiwan",
        "MaxTemp": "25.8",
        "MeanTemp": "21.7",
        "MinTemp": "18.5",
        "Month": 11
    },
    {
        "CTID": "21",
        "CTNM": "Taiwan",
        "MaxTemp": "22.3",
        "MeanTemp": "18.2",
        "MinTemp": "15.1",
        "Month": 12
    }
]
}
